strtool/__init__.py
strtool/abi/ERC20.json
strtool/balancerErrors.py
strtool/balancerv2cad/.gitignore
strtool/balancerv2cad/README.md
strtool/balancerv2cad/notebooks/BalancerV2.ipynb
strtool/balancerv2cad/poetry.lock
strtool/balancerv2cad/pyproject.toml
strtool/balancerv2cad/scripts/project_helper.py
strtool/balancerv2cad/src/balancerv2cad/BalancerConstants.py
strtool/balancerv2cad/src/balancerv2cad/StableMath.py
strtool/balancerv2cad/src/balancerv2cad/StablePool.py
strtool/balancerv2cad/src/balancerv2cad/WeightedMath.py
strtool/balancerv2cad/src/balancerv2cad/WeightedPool.py
strtool/balancerv2cad/src/balancerv2cad/__init__.py
strtool/balancerv2cad/src/balancerv2cad/logger/__init__.py
strtool/balancerv2cad/src/balancerv2cad/logger/pkg_logger.py
strtool/balancerv2cad/src/balancerv2cad/main.py
strtool/balancerv2cad/src/balancerv2cad/util.py
strtool/balancerv2cad/tests/__init__.py
strtool/balancerv2cad/tests/conftest.py
strtool/balancerv2cad/tests/unit-test/test_StableMath.py
strtool/balancerv2cad/tests/unit-test/test_WeightedMath.py
strtool/balancerv2cad/tests/unit-test/test_kickstart.py
strtool/deployments/20230327-authorizer/abi/Authorizer.json
strtool/deployments/20230327-authorizer/output/bnb-test.json
strtool/deployments/20230327-authorizer/output/bnb.json
strtool/deployments/20230327-authorizer/output/goerli.json
strtool/deployments/20230327-composable-stable-pool-v3/abi/ComposableStablePool.json
strtool/deployments/20230327-composable-stable-pool-v3/abi/ComposableStablePoolFactory.json
strtool/deployments/20230327-composable-stable-pool-v3/output/bnb-test.json
strtool/deployments/20230327-composable-stable-pool-v3/output/bnb.json
strtool/deployments/20230327-composable-stable-pool-v3/output/goerli.json
strtool/deployments/20230327-vault/abi/BalancerHelpers.json
strtool/deployments/20230327-vault/abi/Vault.json
strtool/deployments/20230327-vault/output/bnb-test.json
strtool/deployments/20230327-vault/output/bnb.json
strtool-0.1.0.dist-info/METADATA
strtool-0.1.0.dist-info/WHEEL
strtool-0.1.0.dist-info/RECORD
